develocorder/__init__.py
develocorder/graph.py
develocorder/heatmap.py
develocorder/interface.py
develocorder/line_plot.py
develocorder/logger.py
develocorder-0.4.0.dist-info/LICENSE
develocorder-0.4.0.dist-info/METADATA
develocorder-0.4.0.dist-info/WHEEL
develocorder-0.4.0.dist-info/top_level.txt
develocorder-0.4.0.dist-info/RECORD
