Metadata-Version: 2.1
Name: develocorder
Version: 0.4.0
Summary: Simple live value plotter using Matplotlib
Home-page: https://github.com/wahtak/develocorder
Author: Alexander Wah Tak Metz
Author-email: alexander.wt.metz@gmail.com
License: UNKNOWN
Platform: UNKNOWN
Classifier: Programming Language :: Python :: 3
Classifier: License :: OSI Approved :: MIT License
Classifier: Operating System :: OS Independent
Requires-Python: >=3.6
Requires-Dist: numpy
Requires-Dist: matplotlib
